cli/__init__.py
cli/__main__.py
cli/cli.py
cli/plugin_cli.py
dr_web_engine-1.0.1.dist-info/licenses/LICENSE
engine/__init__.py
engine/tests/__init__.py
engine/tests/conftest.py
engine/tests/e2e/test_actions_e2e.py
engine/tests/integration/__init__.py
engine/tests/integration/mock_browser_client.py
engine/tests/integration/test_action_integration.py
engine/tests/integration/test_conditional_integration.py
engine/tests/integration/test_engine_integration.py
engine/tests/unit/__init__.py
engine/tests/unit/test_action_handlers.py
engine/tests/unit/test_actions.py
engine/tests/unit/test_ai_selector.py
engine/tests/unit/test_api_extractor.py
engine/tests/unit/test_conditionals.py
engine/tests/unit/test_engine.py
engine/tests/unit/test_extractor.py
engine/tests/unit/test_follow_processor.py
engine/tests/unit/test_javascript_action.py
engine/tests/unit/test_javascript_processor.py
engine/tests/unit/test_jsonld_extractor.py
engine/tests/unit/test_processors.py
engine/tests/unit/test_smart_retry_plugin.py
engine/tests/unit/test_parsers/__init__.py
engine/tests/unit/test_parsers/test_json5_parser.py
engine/tests/unit/test_parsers/test_yaml_parser.py
engine/web_engine/__init__.py
engine/web_engine/actions.py
engine/web_engine/conditionals.py
engine/web_engine/engine.py
engine/web_engine/extract_processor.py
engine/web_engine/extractor.py
engine/web_engine/follow_processor.py
engine/web_engine/javascript_processor.py
engine/web_engine/models.py
engine/web_engine/plugin_discovery.py
engine/web_engine/plugin_interface.py
engine/web_engine/plugin_manager.py
engine/web_engine/processors.py
engine/web_engine/utils.py
engine/web_engine/base/__init__.py
engine/web_engine/base/browser.py
engine/web_engine/base/extractor.py
engine/web_engine/base/httpx_browser.py
engine/web_engine/base/playwright_browser.py
engine/web_engine/parsers/__init__.py
engine/web_engine/parsers/json5_parser.py
engine/web_engine/parsers/yaml_parser.py
engine/web_engine/plugins/__init__.py
engine/web_engine/plugins/ai_selector.py
dr_web_engine-1.0.1.dist-info/METADATA
dr_web_engine-1.0.1.dist-info/WHEEL
dr_web_engine-1.0.1.dist-info/entry_points.txt
dr_web_engine-1.0.1.dist-info/top_level.txt
dr_web_engine-1.0.1.dist-info/RECORD
