Metadata-Version: 2.4
Name: dr-web-engine
Version: 1.0.1
Summary: A data retrieval engine based on Playwright.
Author-email: Ylli Prifti <ylli@prifti.us>
License:                     GNU GENERAL PUBLIC LICENSE
Requires-Python: >=3.10
License-File: LICENSE
Requires-Dist: playwright
Requires-Dist: pydantic
Requires-Dist: json5
Requires-Dist: pyyaml
Requires-Dist: typer[all]
Requires-Dist: requests
Requires-Dist: rich
Requires-Dist: packaging
Provides-Extra: dev
Requires-Dist: pytest; extra == "dev"
Requires-Dist: pytest-playwright; extra == "dev"
Requires-Dist: pytest-mock; extra == "dev"
Requires-Dist: tomli; extra == "dev"
Dynamic: license-file
